{"count":0,"code":0,"msg":null,"data":[{"Id":59280,"Name":"贵阳 市区风骚少妇","QQ":"2184473947 没见到人一分钱都不要给","Weixin":"没见到人一分钱都不要给","Phone":"没留","JianJie":"樱井利亚，超级服务控，进门摸雀雀，共浴，镜前萧，硬了，拍马上阵，镜前后入，妹子要求，镜前各种抽查，出水。第二次，换制服，全套服务，总体可吻，可舔，舌头很好用，比较会玩骚，检查没有生过，年纪30左右，会保养，胸大d杯，皮肤不错，比较舒服","Price":"6/p 9/pp","FuWu":"口 舌吻","Address":"南明区","City":"贵阳","Remark":"2021-03-11 14:26","Status":null,"UserId":1001,"CreateTime":"\/Date(1615443965430)\/","CreateTimeStr":"2021-03-11 14:26","Money":5,"InfoType":null,"ClickTime":92,"GoodTime":0,"BadTime":0,"ErrorTime":0,"QueryTags":null,"IsDelete":null,"CommentCount":0,"UserName":"王者风范","UserMoney":null,"HeadImg":"/Attach/userHead/6a6b4d0e-08ce-4271-805a-41105cecc727.jpg","LastCommentTime":null,"Pic1":null,"Pic2":null},{"Id":48913,"Name":"贵阳 南明区 绮梦老师","QQ":"380979891","Weixin":"17135271639；","Phone":"18984345309；","JianJie":"服务很巴适 身材也很好","Price":"600一次，800两次","FuWu":"全套服务，口暴，69，可无套但不能内射","Address":"贵阳南明区喷水池附近","City":"贵阳","Remark":"2020-09-20 00:36","Status":null,"UserId":1001,"CreateTime":"\/Date(1600533360513)\/","CreateTimeStr":"2020-09-20 00:36","Money":5,"InfoType":null,"ClickTime":109,"GoodTime":0,"BadTime":0,"ErrorTime":0,"QueryTags":null,"IsDelete":null,"CommentCount":0,"UserName":"王者风范","UserMoney":null,"HeadImg":"/Attach/userHead/6a6b4d0e-08ce-4271-805a-41105cecc727.jpg","LastCommentTime":null,"Pic1":null,"Pic2":null}]}