{"count":0,"code":0,"msg":null,"data":[{"Id":59421,"Name":"西安 莲湖锦里30岁熟女小鱼","QQ":null,"Weixin":" 13152060626；","Phone":" 13152060626；","JianJie":"嫂子自己有地方，挺干净的，还有玩具和道具，整体还可以，嫂子也很配合，还可以玩Sm","Price":"500-1000","FuWu":"情趣房，八爪椅，弹力球，各种情趣道具，高跟丝袜，制服诱惑，连吹带做，6.9等，深喉口爆，胸推漫游，毒龙，角色扮演","Address":"陕西省西安市莲湖区农兴路6号","City":"西安","Remark":"2021-03-13 13:23","Status":null,"UserId":1001,"CreateTime":"\/Date(1615613020873)\/","CreateTimeStr":"2021-03-13 13:23","Money":5,"InfoType":null,"ClickTime":310,"GoodTime":0,"BadTime":0,"ErrorTime":0,"QueryTags":null,"IsDelete":null,"CommentCount":0,"UserName":"王者风范","UserMoney":null,"HeadImg":"/Attach/userHead/6a6b4d0e-08ce-4271-805a-41105cecc727.jpg","LastCommentTime":null,"Pic1":"http://feng321.cn:89/UpLoadFiles\\20210313132435.jpg","Pic2":null},{"Id":59123,"Name":"西安 雁塔区 熟女","QQ":"2826788602","Weixin":"aoe195915","Phone":"19591570952","JianJie":"目测年龄35+吧。去西安出差朋友推荐的，还可以。她还有一个年轻的室友，可以去看看选哪个。服务还可以，喜欢熟女的去","Price":"4p 6pp 8by（不限）","FuWu":"全套","Address":"陕西省西安市雁塔区长安南路168号（象牙宫寓）","City":"西安","Remark":"2021-03-08 19:10","Status":null,"UserId":1001,"CreateTime":"\/Date(1615201800077)\/","CreateTimeStr":"2021-03-08 19:10","Money":5,"InfoType":null,"ClickTime":206,"GoodTime":0,"BadTime":0,"ErrorTime":0,"QueryTags":null,"IsDelete":null,"CommentCount":0,"UserName":"王者风范","UserMoney":null,"HeadImg":"/Attach/userHead/6a6b4d0e-08ce-4271-805a-41105cecc727.jpg","LastCommentTime":null,"Pic1":"http://feng321.cn:89/UpLoadFiles\\20210308191009.jpg","Pic2":"http://feng321.cn:89/UpLoadFiles\\20210308191101.jpg"},{"Id":58498,"Name":"西安 北郊短发妹","QQ":null,"Weixin":"huaerjiejieya2020","Phone":"没留","JianJie":"北郊一个大的楼凤群里加的妹子，因为比较喜欢短发，所以一下子她就映入眼帘.到地方后妹子和照片基本无差，整个服务过程也非常OK尤其是妹子上位时候短发特别有感觉。整体来说这个再我玩过的LF里性价比属于中上等","Price":"500p  700pp","FuWu":" 全套，KB，DP","Address":"陕西省西安市未央区常青二路 紫薇开元盛世","City":"西安","Remark":"2021-02-27 10:44","Status":null,"UserId":1001,"CreateTime":"\/Date(1614393884210)\/","CreateTimeStr":"2021-02-27 10:44","Money":5,"InfoType":null,"ClickTime":382,"GoodTime":2,"BadTime":0,"ErrorTime":0,"QueryTags":null,"IsDelete":null,"CommentCount":0,"UserName":"王者风范","UserMoney":null,"HeadImg":"/Attach/userHead/6a6b4d0e-08ce-4271-805a-41105cecc727.jpg","LastCommentTime":null,"Pic1":"http://feng321.cn:89/UpLoadFiles\\20210227104521.jpg","Pic2":"http://feng321.cn:89/UpLoadFiles\\20210227104528.jpg"},{"Id":56505,"Name":"西安 北郊 小甜甜 可双飞","QQ":null,"Weixin":"WRMY123","Phone":"没留","JianJie":"20岁 身高165cm 体重94斤 胸围36C","Price":"500一次 ","FuWu":"全套服务都有","Address":" 名京九合院(西安市未央区) 陕西省西安市未央区萧家北巷","City":"西安","Remark":"2021-01-17 19:53","Status":null,"UserId":1001,"CreateTime":"\/Date(1610884392327)\/","CreateTimeStr":"2021-01-17 19:53","Money":5,"InfoType":null,"ClickTime":247,"GoodTime":0,"BadTime":0,"ErrorTime":0,"QueryTags":null,"IsDelete":null,"CommentCount":0,"UserName":"王者风范","UserMoney":null,"HeadImg":"/Attach/userHead/6a6b4d0e-08ce-4271-805a-41105cecc727.jpg","LastCommentTime":null,"Pic1":null,"Pic2":null},{"Id":55959,"Name":"陕西省铜川市有资源吗如题","QQ":null,"Weixin":null,"Phone":null,"JianJie":null,"Price":null,"FuWu":null,"Address":null,"City":"铜川","Remark":"2021-01-11 22:55","Status":null,"UserId":71969,"CreateTime":"\/Date(1610376957840)\/","CreateTimeStr":"2021-01-11 22:55","Money":null,"InfoType":null,"ClickTime":24,"GoodTime":0,"BadTime":0,"ErrorTime":0,"QueryTags":null,"IsDelete":null,"CommentCount":0,"UserName":"小小小娃子","UserMoney":null,"HeadImg":null,"LastCommentTime":"\/Date(1610376957840)\/","Pic1":null,"Pic2":null},{"Id":54888,"Name":"西安 未央区龙首村 邻家小妹","QQ":null,"Weixin":"wx5876185","Phone":"15137026133","JianJie":"性感小姐姐，服务到位温柔有耐心，口活好，让你体验高端品味","Price":"400一次 700两次","FuWu":"洗吹胸推口吹接吻制服丝袜指划69按摩推波","Address":"陕西省西安市未央区龙首村印象城","City":"西安","Remark":"2020-12-17 21:50","Status":null,"UserId":1001,"CreateTime":"\/Date(1608213050367)\/","CreateTimeStr":"2020-12-17 21:50","Money":5,"InfoType":null,"ClickTime":215,"GoodTime":0,"BadTime":0,"ErrorTime":0,"QueryTags":null,"IsDelete":null,"CommentCount":0,"UserName":"王者风范","UserMoney":null,"HeadImg":"/Attach/userHead/6a6b4d0e-08ce-4271-805a-41105cecc727.jpg","LastCommentTime":null,"Pic1":"http://207.148.43.152:89/UpLoadFiles\\20201217215233.jpg","Pic2":"http://207.148.43.152:89/UpLoadFiles\\20201217215240.jpg"},{"Id":53839,"Name":"西安 北郊 小苹果 E罩杯 ","QQ":"2275828633","Weixin":null,"Phone":"没留","JianJie":"南方MM ；身高160； 体重45kg ；自己有窝 ；芳龄27 ；36E","Price":"500一次 900两次  2000包夜","FuWu":"鸳鸯浴 无套吹箫 深喉 调情风骚 波推 六九式吹箫  性爱十八式爱爱","Address":"印象城购物中心(未央路店) 陕西省西安市未央区末央路 33号","City":"西安","Remark":"2020-11-25 13:38","Status":null,"UserId":1001,"CreateTime":"\/Date(1606282736733)\/","CreateTimeStr":"2020-11-25 13:38","Money":5,"InfoType":null,"ClickTime":227,"GoodTime":0,"BadTime":0,"ErrorTime":0,"QueryTags":null,"IsDelete":null,"CommentCount":0,"UserName":"王者风范","UserMoney":null,"HeadImg":"/Attach/userHead/6a6b4d0e-08ce-4271-805a-41105cecc727.jpg","LastCommentTime":null,"Pic1":"http://207.148.43.152:89/UpLoadFiles\\20201125133916.jpg","Pic2":null},{"Id":52889,"Name":"西安 雁塔区 新人甜甜","QQ":null,"Weixin":"zxz1990ljg","Phone":"16562371060","JianJie":"22岁  身高165  体重50kg  胸围36D","Price":"500一次 1000两次 包夜2000","FuWu":"鸳鸯浴 无套吹箫 深喉 调情风骚 波推 六九式吹箫  性爱十八式爱爱","Address":" 西旅国际中心 陕西省西安市雁塔区长安中路与兴善寺东街交叉口东北方向","City":"西安","Remark":"2020-11-05 16:31","Status":null,"UserId":1001,"CreateTime":"\/Date(1604565077397)\/","CreateTimeStr":"2020-11-05 16:31","Money":5,"InfoType":null,"ClickTime":513,"GoodTime":0,"BadTime":0,"ErrorTime":0,"QueryTags":null,"IsDelete":null,"CommentCount":1,"UserName":"王者风范","UserMoney":null,"HeadImg":"/Attach/userHead/6a6b4d0e-08ce-4271-805a-41105cecc727.jpg","LastCommentTime":"\/Date(1614252399920)\/","Pic1":"http://207.148.43.152:89/UpLoadFiles\\20201105163138.jpg","Pic2":"http://207.148.43.152:89/UpLoadFiles\\20201105163144.jpg"},{"Id":52810,"Name":"西安 未央区 菱菱","QQ":null,"Weixin":"zh687021","Phone":"没留","JianJie":"23岁  身高167cm  体重95斤  胸围36C","Price":"600一次  1100两次  包夜2200","FuWu":"鸳鸯浴 无套吹箫 深喉 调情风骚 波推 六九式吹箫  性爱十八式爱爱","Address":" 宫园中央5号楼 陕西省西安市未央区","City":"西安","Remark":"2020-11-03 23:17","Status":null,"UserId":1001,"CreateTime":"\/Date(1604416678623)\/","CreateTimeStr":"2020-11-03 23:17","Money":5,"InfoType":null,"ClickTime":357,"GoodTime":0,"BadTime":0,"ErrorTime":0,"QueryTags":null,"IsDelete":null,"CommentCount":0,"UserName":"王者风范","UserMoney":null,"HeadImg":"/Attach/userHead/6a6b4d0e-08ce-4271-805a-41105cecc727.jpg","LastCommentTime":null,"Pic1":"http://207.148.43.152:89/UpLoadFiles\\20201103231901.jpg","Pic2":"http://207.148.43.152:89/UpLoadFiles\\20201103231908.jpg"},{"Id":52740,"Name":"西安 未央区宫园中央 安娜","QQ":null,"Weixin":"ping835888","Phone":"没留","JianJie":"24岁 身高166  体重100斤  胸围36B","Price":"500一次 900两次  2300包夜","FuWu":"鸳鸯浴 无套吹箫 深喉 调情风骚 波推 六九式吹箫  性爱十八式爱爱","Address":"宫园中央2期 陕西省西安市未央区未央路103号附近","City":"西安","Remark":"2020-11-02 14:55","Status":null,"UserId":1001,"CreateTime":"\/Date(1604300127247)\/","CreateTimeStr":"2020-11-02 14:55","Money":5,"InfoType":null,"ClickTime":196,"GoodTime":0,"BadTime":0,"ErrorTime":0,"QueryTags":null,"IsDelete":null,"CommentCount":0,"UserName":"王者风范","UserMoney":null,"HeadImg":"/Attach/userHead/6a6b4d0e-08ce-4271-805a-41105cecc727.jpg","LastCommentTime":null,"Pic1":"http://207.148.43.152:89/UpLoadFiles\\20201102145607.jpg","Pic2":"http://207.148.43.152:89/UpLoadFiles\\20201102145612.jpg"},{"Id":52538,"Name":"西安 碑林区东关正街 王姐鸡头","QQ":"3058687820","Weixin":"18189148053","Phone":"18392650922；18189148053","JianJie":"手下有好几个妹子的，便宜实惠，适合泻火","Price":"150一次","FuWu":"快餐","Address":"人人乐超市(东门购物广场店) 陕西省西安市碑林区东关正街121号","City":"西安","Remark":"2020-10-29 13:25","Status":null,"UserId":1001,"CreateTime":"\/Date(1603949157000)\/","CreateTimeStr":"2020-10-29 13:25","Money":5,"InfoType":null,"ClickTime":106,"GoodTime":0,"BadTime":0,"ErrorTime":0,"QueryTags":null,"IsDelete":null,"CommentCount":0,"UserName":"王者风范","UserMoney":null,"HeadImg":"/Attach/userHead/6a6b4d0e-08ce-4271-805a-41105cecc727.jpg","LastCommentTime":null,"Pic1":null,"Pic2":null},{"Id":52252,"Name":"西安 未央区 新人平面模特","QQ":null,"Weixin":"Tu970810","Phone":"没留","JianJie":"年龄24 身高172 体重99 围36C","Price":"600一次  1100两次 ","FuWu":"全套服务都有","Address":"正新鸡排 陕西省西安市未央区","City":"西安","Remark":"2020-10-22 19:42","Status":null,"UserId":1001,"CreateTime":"\/Date(1603366975017)\/","CreateTimeStr":"2020-10-22 19:42","Money":5,"InfoType":null,"ClickTime":305,"GoodTime":0,"BadTime":0,"ErrorTime":0,"QueryTags":null,"IsDelete":null,"CommentCount":0,"UserName":"王者风范","UserMoney":null,"HeadImg":"/Attach/userHead/6a6b4d0e-08ce-4271-805a-41105cecc727.jpg","LastCommentTime":null,"Pic1":"http://207.148.43.152:89/UpLoadFiles\\20201022194351.jpg","Pic2":"http://207.148.43.152:89/UpLoadFiles\\20201022194359.jpg"},{"Id":51753,"Name":"西安 东郊 四十多的熟妇 风骚得很","QQ":null,"Weixin":"abc15691821593","Phone":"15691821593","JianJie":"服务好，喜欢熟妇年龄大的可以尝试。","Price":"300-800","FuWu":"全套服务都有","Address":"陕西省西安市通化i门附近","City":"西安","Remark":"2020-10-11 21:21","Status":null,"UserId":1001,"CreateTime":"\/Date(1602422482293)\/","CreateTimeStr":"2020-10-11 21:21","Money":5,"InfoType":null,"ClickTime":158,"GoodTime":0,"BadTime":0,"ErrorTime":0,"QueryTags":null,"IsDelete":null,"CommentCount":0,"UserName":"王者风范","UserMoney":null,"HeadImg":"/Attach/userHead/6a6b4d0e-08ce-4271-805a-41105cecc727.jpg","LastCommentTime":null,"Pic1":"http://loufeng321.cn:83/UpLoadFiles\\20201011212201.jpg","Pic2":"http://loufeng321.cn:83/UpLoadFiles\\20201011212208.jpg"},{"Id":49230,"Name":"西安 草滩妹纸 闹闹","QQ":null,"Weixin":"huaduo20191118","Phone":"没留","JianJie":"小黄文不会写 第一次去感觉还不错 短发少妇哈哈哈","Price":"600一次 ","FuWu":"按摩,波推，臀推","Address":"陕西省西安市草滩妹纸经常换地方不确定","City":"西安","Remark":"2020-09-25 14:14","Status":null,"UserId":1001,"CreateTime":"\/Date(1601014481967)\/","CreateTimeStr":"2020-09-25 14:14","Money":5,"InfoType":null,"ClickTime":166,"GoodTime":0,"BadTime":0,"ErrorTime":0,"QueryTags":null,"IsDelete":null,"CommentCount":0,"UserName":"王者风范","UserMoney":null,"HeadImg":"/Attach/userHead/6a6b4d0e-08ce-4271-805a-41105cecc727.jpg","LastCommentTime":null,"Pic1":"http://loufeng321.cn:83/UpLoadFiles\\20200925141506.jpg","Pic2":null},{"Id":46941,"Name":"西安 未央印象城一楼 果果","QQ":null,"Weixin":"yes555566667777","Phone":"没留","JianJie":"23岁 身高160 体重90斤  胸围36C  皮肤白皙  活好不粘人","Price":"500一次 900两次 ","FuWu":"鸳鸯浴 无套吹箫 深喉 调情风骚 波推 六九式吹箫  性爱十八式爱爱","Address":" 星巴克咖啡 陕西省西安市未央区未央路33号未央印象城一楼","City":"西安","Remark":"2020-08-15 20:10","Status":null,"UserId":1001,"CreateTime":"\/Date(1597493447720)\/","CreateTimeStr":"2020-08-15 20:10","Money":5,"InfoType":null,"ClickTime":227,"GoodTime":0,"BadTime":0,"ErrorTime":0,"QueryTags":null,"IsDelete":null,"CommentCount":0,"UserName":"王者风范","UserMoney":null,"HeadImg":"/Attach/userHead/6a6b4d0e-08ce-4271-805a-41105cecc727.jpg","LastCommentTime":null,"Pic1":"http://loufeng321.cn:83/UpLoadFiles\\20200815201132.jpg","Pic2":"http://loufeng321.cn:83/UpLoadFiles\\20200815201141.jpg"},{"Id":46939,"Name":"西安 未央区  名京九合院 新人琪琪 可以双飞","QQ":null,"Weixin":"gxfc34588866","Phone":"没留","JianJie":"24岁 身高166cm  体重102斤  胸围36D ","Price":"500一次 900两次  2000包夜  1500两小时不限次","FuWu":"鸳鸯浴 无套吹箫 深喉 调情风骚 波推 六九式吹箫  性爱十八式爱爱","Address":"范唐life社区食堂 陕西省西安市未央区萧家巷名京九合院锦福苑13号楼四方街1层","City":"西安","Remark":"2020-08-15 18:32","Status":null,"UserId":1001,"CreateTime":"\/Date(1597487566127)\/","CreateTimeStr":"2020-08-15 18:32","Money":5,"InfoType":null,"ClickTime":194,"GoodTime":1,"BadTime":0,"ErrorTime":0,"QueryTags":null,"IsDelete":null,"CommentCount":0,"UserName":"王者风范","UserMoney":null,"HeadImg":"/Attach/userHead/6a6b4d0e-08ce-4271-805a-41105cecc727.jpg","LastCommentTime":null,"Pic1":"http://loufeng321.cn:83/UpLoadFiles\\20200815183306.jpg","Pic2":"http://loufeng321.cn:83/UpLoadFiles\\20200815183313.jpg"},{"Id":46937,"Name":"西安 未央区 小娟娟","QQ":null,"Weixin":"aaa986aaa986aaa","Phone":"没留","JianJie":"25岁 身高171  体重110斤 胸围36B ","Price":"500一次 900两次 ","FuWu":"鸳鸯浴 无套吹箫 深喉 调情风骚 波推 六九式吹箫  性爱十八式爱爱","Address":" 美华母婴月子会所 陕西省西安市未央区未央立交","City":"西安","Remark":"2020-08-15 18:04","Status":null,"UserId":1001,"CreateTime":"\/Date(1597485860950)\/","CreateTimeStr":"2020-08-15 18:04","Money":5,"InfoType":null,"ClickTime":82,"GoodTime":0,"BadTime":0,"ErrorTime":0,"QueryTags":null,"IsDelete":null,"CommentCount":0,"UserName":"王者风范","UserMoney":null,"HeadImg":"/Attach/userHead/6a6b4d0e-08ce-4271-805a-41105cecc727.jpg","LastCommentTime":null,"Pic1":"http://loufeng321.cn:83/UpLoadFiles\\20200815180610.jpg","Pic2":"http://loufeng321.cn:83/UpLoadFiles\\20200815180616.jpg"},{"Id":44568,"Name":"西安 碑林区草场坡 菲菲","QQ":null,"Weixin":"mh6666518","Phone":"没留","JianJie":"美女身高165.体重103.罩杯36B","Price":"500一节700俩节，夜1200（晚十一点到早七点）","FuWu":"吹，啪啪，姿势配合，陪洗，六九，指划，挑逗，丝袜，高跟。","Address":"摩登主场-南门 陕西省西安市碑林区草场坡","City":"西安","Remark":"2020-07-20 18:32","Status":null,"UserId":1001,"CreateTime":"\/Date(1595241129897)\/","CreateTimeStr":"2020-07-20 18:32","Money":5,"InfoType":null,"ClickTime":112,"GoodTime":0,"BadTime":0,"ErrorTime":0,"QueryTags":null,"IsDelete":null,"CommentCount":0,"UserName":"王者风范","UserMoney":null,"HeadImg":"/Attach/userHead/6a6b4d0e-08ce-4271-805a-41105cecc727.jpg","LastCommentTime":null,"Pic1":"http://loufeng321.cn:83/UpLoadFiles\\20200720183230.jpg","Pic2":"http://loufeng321.cn:83/UpLoadFiles\\20200720183237.jpg"},{"Id":44544,"Name":"西安 未央区 36E南方妹子百合","QQ":null,"Weixin":"xiaoqiao7979；xlv4412","Phone":"没留","JianJie":"27岁 身高160  体重45kg  胸围36E","Price":"500一次 900两次  2000包夜","FuWu":"蛇吻bo推丝袜you惑 chui箫 man游 口bao 69式 du龙 互tian「chu水算一 次」各种zi势jie锁","Address":"印象城购物中心(未央路店) 陕西省西安市未央区末央路 33号","City":"西安","Remark":"2020-07-19 23:40","Status":null,"UserId":1001,"CreateTime":"\/Date(1595173255767)\/","CreateTimeStr":"2020-07-19 23:40","Money":5,"InfoType":null,"ClickTime":181,"GoodTime":0,"BadTime":0,"ErrorTime":0,"QueryTags":null,"IsDelete":null,"CommentCount":0,"UserName":"王者风范","UserMoney":null,"HeadImg":"/Attach/userHead/6a6b4d0e-08ce-4271-805a-41105cecc727.jpg","LastCommentTime":null,"Pic1":"http://loufeng321.cn:83/UpLoadFiles\\20200719234211.jpg","Pic2":"http://loufeng321.cn:83/UpLoadFiles\\20200719234218.jpg"},{"Id":44056,"Name":"西安 未央区  名京九合院 小姐姐","QQ":null,"Weixin":"mmzz168168zz","Phone":"没留","JianJie":"重庆妹子  24岁，身高165cm,体重48kg 胸围36D，妹妹活泼可爱，性格开 朗，清纯甜美","Price":"500一次 900两次  2000包夜","FuWu":"诱惑调情，毒龙.吹箫，69，鸳鸯戏 水，高跟鞋，丝袜，情趣衣服，制服诱 惑，爱爱","Address":"树人托管(名京校区) 陕西省西安市未央区二环北路西段名京九合院","City":"西安","Remark":"2020-07-09 23:23","Status":null,"UserId":1001,"CreateTime":"\/Date(1594308191817)\/","CreateTimeStr":"2020-07-09 23:23","Money":5,"InfoType":null,"ClickTime":145,"GoodTime":0,"BadTime":0,"ErrorTime":0,"QueryTags":null,"IsDelete":null,"CommentCount":0,"UserName":"王者风范","UserMoney":null,"HeadImg":"/Attach/userHead/6a6b4d0e-08ce-4271-805a-41105cecc727.jpg","LastCommentTime":null,"Pic1":"http://loufeng321.cn:83/UpLoadFiles\\20200709232431.jpg","Pic2":"http://loufeng321.cn:83/UpLoadFiles\\20200709232443.jpg"},{"Id":44043,"Name":"西安 雁塔区 草莓","QQ":null,"Weixin":"AAwjj1314520","Phone":"没留","JianJie":"25岁 身高165  体重95斤 胸围36C  肤白貌美 身材火辣","Price":"700一次 1100两次","FuWu":"制服诱惑角色扮演 69独龙口爆丝袜高跟鞋情趣","Address":"高新大都荟 陕西省西安市雁塔区科技路与高新四路交汇处西北角","City":"西安","Remark":"2020-07-09 11:27","Status":null,"UserId":1001,"CreateTime":"\/Date(1594265257590)\/","CreateTimeStr":"2020-07-09 11:27","Money":5,"InfoType":null,"ClickTime":70,"GoodTime":0,"BadTime":0,"ErrorTime":0,"QueryTags":null,"IsDelete":null,"CommentCount":0,"UserName":"王者风范","UserMoney":null,"HeadImg":"/Attach/userHead/6a6b4d0e-08ce-4271-805a-41105cecc727.jpg","LastCommentTime":null,"Pic1":"http://loufeng321.cn:83/UpLoadFiles\\20200709112815.jpg","Pic2":"http://loufeng321.cn:83/UpLoadFiles\\20200709112820.jpg"},{"Id":43754,"Name":"西安 未央区常青二路 冰冰","QQ":null,"Weixin":"qiyue52152100","Phone":"没留","JianJie":"年龄24  身高163  体重105  胸围34b","Price":"600一次  1100两次  包夜2200","FuWu":"陪洗的推海遊口69 式丝袜高跟的秀惑激 情啪啪啪妹子温柔体贴","Address":" 紫薇开元盛景西区-北门 陕西省西安市未央区常青二路","City":"西安","Remark":"2020-07-04 22:07","Status":null,"UserId":1001,"CreateTime":"\/Date(1593871642823)\/","CreateTimeStr":"2020-07-04 22:07","Money":5,"InfoType":null,"ClickTime":116,"GoodTime":0,"BadTime":0,"ErrorTime":0,"QueryTags":null,"IsDelete":null,"CommentCount":0,"UserName":"王者风范","UserMoney":null,"HeadImg":"/Attach/userHead/6a6b4d0e-08ce-4271-805a-41105cecc727.jpg","LastCommentTime":null,"Pic1":"http://loufeng321.cn:83\\20200704220739.jpg","Pic2":"http://loufeng321.cn:83\\20200704220744.jpg"},{"Id":43588,"Name":"西安 未央区 凤城三路 一家性价比挺高的丝足","QQ":"金富康影院式足浴养生会馆 陕西省-西安市-未央区-凤城三路东段六号","Weixin":"金富康影院式足浴养生会馆 陕西省-西安市-未央区-凤城三路东段六号","Phone":"金富康影院式足浴养生会馆 陕西省-西安市-未央区-凤城三路东段六号","JianJie":"正规的泡脚按摩做完，开始BA面的各种项目，感觉小姐姐手法可以的，挺有感觉的。但是小姐姐在 正面给我按的时候，总是坐在我的小弟弟上，搞得我很尴尬，难受但不好意思说。最后小姐姐帮着释放了一下。总得来说，36号小姐姐各方面都挺好","Price":"150-350","FuWu":"按摩，诱惑，指压","Address":"金富康影院式足浴养生会馆 陕西省-西安市-未央区-凤城三路东段六号","City":"西安","Remark":"2020-07-02 01:06","Status":null,"UserId":1001,"CreateTime":"\/Date(1593623190750)\/","CreateTimeStr":"2020-07-02 01:06","Money":5,"InfoType":null,"ClickTime":164,"GoodTime":0,"BadTime":0,"ErrorTime":0,"QueryTags":null,"IsDelete":null,"CommentCount":0,"UserName":"王者风范","UserMoney":null,"HeadImg":"/Attach/userHead/6a6b4d0e-08ce-4271-805a-41105cecc727.jpg","LastCommentTime":null,"Pic1":null,"Pic2":null},{"Id":43393,"Name":"西安 未央区 晓鸳","QQ":null,"Weixin":"OPPO100111","Phone":"没留","JianJie":"23岁  165高  95斤  36B  温柔体贴/不催人","Price":"单次/5张(限时50分内) ;双次/9张(限时70分内) ;夜/22张(11-8点) (34次)","FuWu":"洗浴/臀推推/69口葆/ 无套吹制服漫游丝袜高跟 姿势十分配合情人般的爱爱","Address":"紫薇开元盛景西区 陕西省西安市未央区常青二路与开元路交汇处向西正南方向90米","City":"西安","Remark":"2020-06-28 18:07","Status":null,"UserId":1001,"CreateTime":"\/Date(1593338860920)\/","CreateTimeStr":"2020-06-28 18:07","Money":5,"InfoType":null,"ClickTime":266,"GoodTime":1,"BadTime":0,"ErrorTime":0,"QueryTags":null,"IsDelete":null,"CommentCount":0,"UserName":"王者风范","UserMoney":null,"HeadImg":"/Attach/userHead/6a6b4d0e-08ce-4271-805a-41105cecc727.jpg","LastCommentTime":null,"Pic1":"http://loufeng321.cn:83\\20200628180816.jpg","Pic2":"http://loufeng321.cn:83\\20200628180822.jpg"},{"Id":43392,"Name":"西安 碑林区草场坡 倩儿","QQ":null,"Weixin":"zhao889900123","Phone":"没留","JianJie":"年龄20  身高165  体重99  胸围36B","Price":"一节课500；两节课700； 包夜1300","FuWu":"口做姿势配合 陪洗高跟丝袜 可69","Address":"长安壹栋 陕西省西安市碑林区新文巷42号","City":"西安","Remark":"2020-06-28 17:55","Status":null,"UserId":1001,"CreateTime":"\/Date(1593338112553)\/","CreateTimeStr":"2020-06-28 17:55","Money":5,"InfoType":null,"ClickTime":134,"GoodTime":0,"BadTime":0,"ErrorTime":0,"QueryTags":null,"IsDelete":null,"CommentCount":0,"UserName":"王者风范","UserMoney":null,"HeadImg":"/Attach/userHead/6a6b4d0e-08ce-4271-805a-41105cecc727.jpg","LastCommentTime":null,"Pic1":"http://loufeng321.cn:83\\20200628175749.jpg","Pic2":"http://loufeng321.cn:83\\20200628175823.jpg"},{"Id":43207,"Name":"西安 碑林区草场坡 香香","QQ":null,"Weixin":"qiaodashanliang","Phone":"没留","JianJie":"27岁 身高170  胸围36D  身材好  服务态度好","Price":"500一次 700两次   包夜1300","FuWu":"照片上有写","Address":"国王的朋友艺术教育(省体校区) 陕西省西安市碑林区草场坡长安三号C座","City":"西安","Remark":"2020-06-24 16:59","Status":null,"UserId":1001,"CreateTime":"\/Date(1592989145677)\/","CreateTimeStr":"2020-06-24 16:59","Money":5,"InfoType":null,"ClickTime":433,"GoodTime":0,"BadTime":0,"ErrorTime":0,"QueryTags":null,"IsDelete":null,"CommentCount":1,"UserName":"王者风范","UserMoney":null,"HeadImg":"/Attach/userHead/6a6b4d0e-08ce-4271-805a-41105cecc727.jpg","LastCommentTime":"\/Date(1593263675503)\/","Pic1":"http://loufeng321.cn:83\\20200624170021.jpg","Pic2":null},{"Id":43203,"Name":"西安 未央区 妮妮","QQ":null,"Weixin":"fuxingzhen789","Phone":"没留","JianJie":"25岁 身高165  体重105斤 胸围36C","Price":"500一次 900两次  2000包夜","FuWu":"鸳鸯浴 无套吹箫 深喉 调情风骚 波推 六九式吹箫  性爱十八式爱爱","Address":"名京九合院9号楼 陕西省西安市未央区","City":"西安","Remark":"2020-06-24 15:56","Status":null,"UserId":1001,"CreateTime":"\/Date(1592985360597)\/","CreateTimeStr":"2020-06-24 15:56","Money":5,"InfoType":null,"ClickTime":205,"GoodTime":0,"BadTime":0,"ErrorTime":0,"QueryTags":null,"IsDelete":null,"CommentCount":0,"UserName":"王者风范","UserMoney":null,"HeadImg":"/Attach/userHead/6a6b4d0e-08ce-4271-805a-41105cecc727.jpg","LastCommentTime":null,"Pic1":"http://loufeng321.cn:83\\20200624155752.jpg","Pic2":"http://loufeng321.cn:83\\20200624155758.jpg"},{"Id":42661,"Name":"西安 城北客运站大明宫西 娇娇","QQ":null,"Weixin":"zanq5201314wl","Phone":"没留","JianJie":"川妹子，22岁 净身高167cm体重55kg，胸围38c，妹妹温柔 体贴，性格开朗，清纯甜美","Price":"500一次 900两次  2000包夜","FuWu":"诱惑调情， Kou爆，胸推,臀推，指划，鸳鸯戏水，爱 爱各种姿势都配合。","Address":"陕西省西安市未央区未央路与北二环十 字西南角名京九合院7号楼2单元","City":"西安","Remark":"2020-06-14 15:52","Status":null,"UserId":1001,"CreateTime":"\/Date(1592121134777)\/","CreateTimeStr":"2020-06-14 15:52","Money":5,"InfoType":null,"ClickTime":247,"GoodTime":0,"BadTime":0,"ErrorTime":0,"QueryTags":null,"IsDelete":null,"CommentCount":0,"UserName":"王者风范","UserMoney":null,"HeadImg":"/Attach/userHead/6a6b4d0e-08ce-4271-805a-41105cecc727.jpg","LastCommentTime":null,"Pic1":"http://loufeng321.cn:83\\20200614155238.jpg","Pic2":"http://loufeng321.cn:83\\20200614155243.jpg"},{"Id":42660,"Name":"西安 未央区大明宫西 黎小洛","QQ":"2099256094","Weixin":"13309249382","Phone":"13309249382","JianJie":"25岁 身高165  体重95  胸围36D","Price":"500一次 800两次","FuWu":"鸳鸯浴 无套吹箫 深喉 调情风骚 波推 六九式吹箫  性爱十八式爱爱","Address":"宫园中央-东1门 陕西省西安市未央区大明宫西地铁站D东北口东200米","City":"西安","Remark":"2020-06-14 15:27","Status":null,"UserId":1001,"CreateTime":"\/Date(1592119657260)\/","CreateTimeStr":"2020-06-14 15:27","Money":5,"InfoType":null,"ClickTime":105,"GoodTime":0,"BadTime":0,"ErrorTime":0,"QueryTags":null,"IsDelete":null,"CommentCount":0,"UserName":"王者风范","UserMoney":null,"HeadImg":"/Attach/userHead/6a6b4d0e-08ce-4271-805a-41105cecc727.jpg","LastCommentTime":null,"Pic1":"http://loufeng321.cn:83\\20200614152823.jpg","Pic2":"http://loufeng321.cn:83\\20200614152830.jpg"},{"Id":42659,"Name":"西安 未央区 名京九合院 菲菲","QQ":null,"Weixin":"zyk777888999","Phone":"没留","JianJie":"23岁 身高164  体重95斤  胸围36D  ","Price":"600一次 1100两次 包夜2200","FuWu":"鸳鸯浴 无套吹箫 深喉 调情风骚 波推 六九式吹箫  性爱十八式爱爱","Address":"名京九合院 陕西省西安市未央区未央路与北二环路交叉口西南侧","City":"西安","Remark":"2020-06-14 15:23","Status":null,"UserId":1001,"CreateTime":"\/Date(1592119390307)\/","CreateTimeStr":"2020-06-14 15:23","Money":5,"InfoType":null,"ClickTime":172,"GoodTime":0,"BadTime":0,"ErrorTime":0,"QueryTags":null,"IsDelete":null,"CommentCount":0,"UserName":"王者风范","UserMoney":null,"HeadImg":"/Attach/userHead/6a6b4d0e-08ce-4271-805a-41105cecc727.jpg","LastCommentTime":null,"Pic1":"http://loufeng321.cn:83\\20200614152317.jpg","Pic2":"http://loufeng321.cn:83\\20200614152324.jpg"},{"Id":42411,"Name":"西安 名京九合院 不二姑娘","QQ":"19165843791 加支付宝聊","Weixin":"19165843791 加支付宝聊","Phone":"19165843791 加支付宝聊","JianJie":"19岁，身高165cm，体重48kg，胸围B,妹妹活泼可爱，性格开朗， 清纯甜 美","Price":"500一次 900两次  2000包夜","FuWu":"诱惑调情， 独龙 69.。吹箫，鸳鸯戏水，爱 爱 各种姿势","Address":"名京九合院 陕西省西安市未央区未央路与北二环路交叉口西南侧","City":"西安","Remark":"2020-06-08 23:58","Status":null,"UserId":1001,"CreateTime":"\/Date(1591631926777)\/","CreateTimeStr":"2020-06-08 23:58","Money":5,"InfoType":null,"ClickTime":143,"GoodTime":0,"BadTime":0,"ErrorTime":0,"QueryTags":null,"IsDelete":null,"CommentCount":0,"UserName":"王者风范","UserMoney":null,"HeadImg":"/Attach/userHead/6a6b4d0e-08ce-4271-805a-41105cecc727.jpg","LastCommentTime":null,"Pic1":"http://loufeng321.cn:83\\20200608235915.jpg","Pic2":"http://loufeng321.cn:83\\20200608235922.jpg"},{"Id":41999,"Name":"西安 未央区 新人 花花","QQ":null,"Weixin":"yangchuxin88","Phone":"没留","JianJie":"21岁 身高167  体重120斤  胸围36D","Price":"500一次 900两次 ","FuWu":"鸳鸯浴 无套吹箫 深喉 调情风骚 波推 六九式吹箫  性爱十八式爱爱","Address":"宫园中央2号楼 陕西省西安市未央区","City":"西安","Remark":"2020-05-30 12:06","Status":null,"UserId":1001,"CreateTime":"\/Date(1590811587847)\/","CreateTimeStr":"2020-05-30 12:06","Money":5,"InfoType":null,"ClickTime":114,"GoodTime":0,"BadTime":0,"ErrorTime":0,"QueryTags":null,"IsDelete":null,"CommentCount":0,"UserName":"王者风范","UserMoney":null,"HeadImg":"/Attach/userHead/6a6b4d0e-08ce-4271-805a-41105cecc727.jpg","LastCommentTime":null,"Pic1":"http://loufeng321.cn:83\\20200530120648.jpg","Pic2":"http://loufeng321.cn:83\\20200530120654.jpg"},{"Id":41995,"Name":"西安 未央区 印象城购物中心 安妮","QQ":null,"Weixin":"C17772428075","Phone":"没留","JianJie":"联系好了就到了进门一看本人和照片不差，身材很棒吧，打了她屁股摸摸舒服，过程不说了，自己体会！","Price":"400一次 700两次","FuWu":"鸳鸯浴 无套吹箫 深喉 调情风骚 波推 六九式吹箫  性爱十八式爱爱","Address":"印象城购物中心 陕西省西安市未央区未央路33号","City":"西安","Remark":"2020-05-29 23:28","Status":null,"UserId":1001,"CreateTime":"\/Date(1590766107713)\/","CreateTimeStr":"2020-05-29 23:28","Money":5,"InfoType":null,"ClickTime":307,"GoodTime":1,"BadTime":0,"ErrorTime":0,"QueryTags":null,"IsDelete":null,"CommentCount":0,"UserName":"王者风范","UserMoney":null,"HeadImg":"/Attach/userHead/6a6b4d0e-08ce-4271-805a-41105cecc727.jpg","LastCommentTime":null,"Pic1":"http://loufeng321.cn:83\\20200529232858.jpg","Pic2":"http://loufeng321.cn:83\\20200529232904.jpg"},{"Id":41992,"Name":"西安 雁塔区乐游东路 新人 小可爱","QQ":null,"Weixin":"fyyzy5321","Phone":"没留","JianJie":"23岁 身高164  体重108斤  胸围36B  丰满型 风骚型  活泼可爱 性格开朗  清纯甜美","Price":"500一次 900两次  2000包夜","FuWu":"鸳鸯浴 无套吹箫 深喉 调情风骚 波推 六九式吹箫  性爱十八式爱爱","Address":"后村嘉园(南门) 陕西省西安市雁塔区乐游东路","City":"西安","Remark":"2020-05-29 22:43","Status":null,"UserId":1001,"CreateTime":"\/Date(1590763391753)\/","CreateTimeStr":"2020-05-29 22:43","Money":5,"InfoType":null,"ClickTime":222,"GoodTime":0,"BadTime":0,"ErrorTime":0,"QueryTags":null,"IsDelete":null,"CommentCount":0,"UserName":"王者风范","UserMoney":null,"HeadImg":"/Attach/userHead/6a6b4d0e-08ce-4271-805a-41105cecc727.jpg","LastCommentTime":null,"Pic1":"http://loufeng321.cn:83\\20200529224513.jpg","Pic2":"http://loufeng321.cn:83\\20200529224521.jpg"},{"Id":41962,"Name":"西安 雁塔区乐游路 果果","QQ":"1005339492","Weixin":"kkmm17726","Phone":"17515767123","JianJie":"联系好了就到了进门一看本人和照片不差，身材很棒吧，打了她屁股摸摸舒服，过程不说了，自己体会！","Price":"500一次","FuWu":"鸳鸯浴 无套吹箫 深喉 调情风骚 波推 六九式吹箫  性爱十八式爱爱","Address":"后村小区二期 陕西省西安市雁塔区乐游路","City":"西安","Remark":"2020-05-29 11:05","Status":null,"UserId":1001,"CreateTime":"\/Date(1590721553800)\/","CreateTimeStr":"2020-05-29 11:05","Money":5,"InfoType":null,"ClickTime":72,"GoodTime":0,"BadTime":0,"ErrorTime":0,"QueryTags":null,"IsDelete":null,"CommentCount":0,"UserName":"王者风范","UserMoney":null,"HeadImg":"/Attach/userHead/6a6b4d0e-08ce-4271-805a-41105cecc727.jpg","LastCommentTime":null,"Pic1":"http://loufeng321.cn:83\\20200529110617.jpg","Pic2":"http://loufeng321.cn:83\\20200529110623.jpg"},{"Id":40548,"Name":"西安 未央区 萧家巷名京九合院  小婷婷","QQ":null,"Weixin":"liuzhi2118","Phone":"没留","JianJie":"清纯少女 来自长沙。岗下水  年龄22岁 净身高166  体重96斤   胸围34b. 活泼可爱。性格开朗。皮肤白嫩清纯甜美。","Price":"5张一次50分钟。9张两次80分钟， 夜价20, 12点到草上9点。","FuWu":"诱惑调情吹箫可无套.毒龙漫游，鸳鸯水。 爱爱配合各种姿势。","Address":"避风港度假公寓 陕西省西安市未央区萧家巷名京九合院13号A楼1单元4层","City":"西安","Remark":"2020-05-16 18:42","Status":null,"UserId":1001,"CreateTime":"\/Date(1589625720013)\/","CreateTimeStr":"2020-05-16 18:42","Money":5,"InfoType":null,"ClickTime":636,"GoodTime":1,"BadTime":0,"ErrorTime":0,"QueryTags":null,"IsDelete":null,"CommentCount":0,"UserName":"王者风范","UserMoney":null,"HeadImg":"/Attach/userHead/6a6b4d0e-08ce-4271-805a-41105cecc727.jpg","LastCommentTime":null,"Pic1":"http://loufeng321.cn:83\\20200516184219.jpg","Pic2":"http://loufeng321.cn:83\\20200516184224.jpg"},{"Id":40394,"Name":"西安 未央区  盛龙广场  小青","QQ":null,"Weixin":"Maxblacker；star20190322","Phone":"没留","JianJie":"23岁 身高165cm  体重50Kg  胸围34D","Price":"单次500/50分钟内   两次1000/100分钟内","FuWu":"无套口B，胸推，臀推，漫游，丝 袜，制服，69，KB，按摩，鸳鸯戏水，姿势 随意，配合度高","Address":" 盛龙广场B区五单元 陕西省西安市未央区未央路80号","City":"西安","Remark":"2020-05-12 11:11","Status":null,"UserId":1001,"CreateTime":"\/Date(1589253061113)\/","CreateTimeStr":"2020-05-12 11:11","Money":5,"InfoType":null,"ClickTime":134,"GoodTime":0,"BadTime":0,"ErrorTime":0,"QueryTags":null,"IsDelete":null,"CommentCount":0,"UserName":"王者风范","UserMoney":null,"HeadImg":"/Attach/userHead/6a6b4d0e-08ce-4271-805a-41105cecc727.jpg","LastCommentTime":null,"Pic1":"http://loufeng321.cn:83\\20200512111146.jpg","Pic2":"http://loufeng321.cn:83\\20200512111154.jpg"},{"Id":40270,"Name":"西安 碑林区新文巷 丑丑","QQ":null,"Weixin":"y26866365","Phone":"没留","JianJie":"25岁 身高168 体重98斤 胸围36B 身材高挑性感  真人和照片基本没差别","Price":"500一次 700两次  ","FuWu":"鸳鸯浴 无套口 制服诱惑 丝袜美腿 任意姿势啪啪","Address":"长安壹栋 陕西省西安市碑林区新文巷42号","City":"西安","Remark":"2020-05-07 17:59","Status":null,"UserId":1001,"CreateTime":"\/Date(1588845557410)\/","CreateTimeStr":"2020-05-07 17:59","Money":5,"InfoType":null,"ClickTime":130,"GoodTime":0,"BadTime":0,"ErrorTime":0,"QueryTags":null,"IsDelete":null,"CommentCount":0,"UserName":"王者风范","UserMoney":null,"HeadImg":"/Attach/userHead/6a6b4d0e-08ce-4271-805a-41105cecc727.jpg","LastCommentTime":null,"Pic1":"http://loufeng321.cn:83\\20200507175952.jpg","Pic2":"http://loufeng321.cn:83\\20200507180020.jpg"},{"Id":40269,"Name":"西安 南郊 电视塔 新人咪咪","QQ":"242027258","Weixin":null,"Phone":"没留","JianJie":"21岁 身高170  体重98斤  胸围C","Price":"400一次 700两次","FuWu":"可口b，陪洗，放松按摩，制服丝 袜,胸推挑逗，指划口活，戴套爱","Address":" 中国,陕西省,西安市,雁塔区 长安南路81号  华城万象二期","City":"西安","Remark":"2020-05-07 17:48","Status":null,"UserId":1001,"CreateTime":"\/Date(1588844900160)\/","CreateTimeStr":"2020-05-07 17:48","Money":5,"InfoType":null,"ClickTime":257,"GoodTime":0,"BadTime":0,"ErrorTime":0,"QueryTags":null,"IsDelete":null,"CommentCount":1,"UserName":"王者风范","UserMoney":null,"HeadImg":"/Attach/userHead/6a6b4d0e-08ce-4271-805a-41105cecc727.jpg","LastCommentTime":"\/Date(1593743189627)\/","Pic1":"http://loufeng321.cn:83\\20200507174856.jpg","Pic2":"http://loufeng321.cn:83\\20200507174901.jpg"},{"Id":40128,"Name":"西安 莲湖区 自强西路 佳儿","QQ":null,"Weixin":"yuehuia7788","Phone":"没留","JianJie":"25岁 身高160  体重95斤  胸围36C  皮肤白嫩","Price":"500一次 900两次  2000包夜","FuWu":"鸳鸯浴 无套吹箫 深喉 调情风骚 波推 六九式吹箫  性爱十八式爱爱","Address":"吉祥凤凰 陕西省西安市莲湖区自强西路","City":"西安","Remark":"2020-05-01 17:39","Status":null,"UserId":1001,"CreateTime":"\/Date(1588325988633)\/","CreateTimeStr":"2020-05-01 17:39","Money":5,"InfoType":null,"ClickTime":190,"GoodTime":0,"BadTime":0,"ErrorTime":0,"QueryTags":null,"IsDelete":null,"CommentCount":0,"UserName":"王者风范","UserMoney":null,"HeadImg":"/Attach/userHead/6a6b4d0e-08ce-4271-805a-41105cecc727.jpg","LastCommentTime":null,"Pic1":"http://loufeng321.cn:83\\20200501174013.jpg","Pic2":"http://loufeng321.cn:83\\20200501174020.jpg"},{"Id":39898,"Name":"西安 北门 南方姑娘 小语","QQ":null,"Weixin":"qiangxinyan","Phone":"没留","JianJie":"23岁 身高165  体重96  胸围36C  态度良好  不催人","Price":"500一次（50分钟）、 900两次 （70分钟）","FuWu":"鸳鸯浴 无套吹箫 深喉 调情风骚 波推 六九式吹箫  性爱十八式爱爱","Address":"陕西省西安市莲湖区自强西路","City":"西安","Remark":"2020-04-24 20:53","Status":null,"UserId":1001,"CreateTime":"\/Date(1587732815583)\/","CreateTimeStr":"2020-04-24 20:53","Money":5,"InfoType":null,"ClickTime":196,"GoodTime":0,"BadTime":0,"ErrorTime":0,"QueryTags":null,"IsDelete":null,"CommentCount":0,"UserName":"王者风范","UserMoney":null,"HeadImg":"/Attach/userHead/6a6b4d0e-08ce-4271-805a-41105cecc727.jpg","LastCommentTime":null,"Pic1":"http://loufeng321.cn:83\\20200424205545.jpg","Pic2":"http://loufeng321.cn:83\\20200424205552.jpg"},{"Id":39897,"Name":"西安 碑林区永宁路 啵啵","QQ":null,"Weixin":"f18629608779","Phone":"没留","JianJie":"24岁 身高162  体重86斤 胸围36C","Price":"500一次50分钟、 900两次 80分钟","FuWu":"鸳鸯浴 无套吹箫 深喉 调情风骚 波推 六九式吹箫  性爱十八式爱爱","Address":"唐久便利 陕西省西安市碑林区永宁路","City":"西安","Remark":"2020-04-24 20:52","Status":null,"UserId":1001,"CreateTime":"\/Date(1587732720987)\/","CreateTimeStr":"2020-04-24 20:52","Money":5,"InfoType":null,"ClickTime":141,"GoodTime":0,"BadTime":0,"ErrorTime":0,"QueryTags":null,"IsDelete":null,"CommentCount":0,"UserName":"王者风范","UserMoney":null,"HeadImg":"/Attach/userHead/6a6b4d0e-08ce-4271-805a-41105cecc727.jpg","LastCommentTime":null,"Pic1":"http://loufeng321.cn:83\\20200424205232.jpg","Pic2":"http://loufeng321.cn:83\\20200424205305.jpg"},{"Id":39895,"Name":"西安 碑林区  中贸广场  小仙女","QQ":null,"Weixin":"Z199912345Z","Phone":"没留","JianJie":"23岁 身高164  体重46kg  胸围C ","Price":"600一次，800两次，1200包夜 ","FuWu":"胸推，漫游，指划耳语，69，口爆，打泡，冰火。","Address":"中贸广场15栋三单元 陕西省西安市碑林区","City":"西安","Remark":"2020-04-24 20:39","Status":null,"UserId":1001,"CreateTime":"\/Date(1587731945020)\/","CreateTimeStr":"2020-04-24 20:39","Money":5,"InfoType":null,"ClickTime":180,"GoodTime":0,"BadTime":0,"ErrorTime":0,"QueryTags":null,"IsDelete":null,"CommentCount":0,"UserName":"王者风范","UserMoney":null,"HeadImg":"/Attach/userHead/6a6b4d0e-08ce-4271-805a-41105cecc727.jpg","LastCommentTime":null,"Pic1":"http://loufeng321.cn:83\\20200424203943.jpg","Pic2":"http://loufeng321.cn:83\\20200424203952.jpg"},{"Id":39771,"Name":"西安 碑林区 南广济街  甜甜","QQ":"1196997086","Weixin":"whr18883037530","Phone":"没留","JianJie":"26岁 身高167  体重108  胸围36G  身材火辣性感  ","Price":"单次500  双次800   夜1500","FuWu":"鸳鸯浴 无套吹箫 深喉 调情风骚 波推 六九式吹箫  性爱十八式爱爱","Address":"荣民国际商务大厦 陕西省西安市碑林区南广济街94号","City":"西安","Remark":"2020-04-20 14:54","Status":null,"UserId":1001,"CreateTime":"\/Date(1587365672317)\/","CreateTimeStr":"2020-04-20 14:54","Money":5,"InfoType":null,"ClickTime":233,"GoodTime":0,"BadTime":0,"ErrorTime":0,"QueryTags":null,"IsDelete":null,"CommentCount":0,"UserName":"王者风范","UserMoney":null,"HeadImg":"/Attach/userHead/6a6b4d0e-08ce-4271-805a-41105cecc727.jpg","LastCommentTime":null,"Pic1":"http://loufeng321.cn:83\\20200420145518.jpg","Pic2":"http://loufeng321.cn:83\\20200420145525.jpg"},{"Id":39593,"Name":"西安 丈八北路 甜甜","QQ":null,"Weixin":"wxtt587963","Phone":"没留","JianJie":"25岁 身高160  体重90斤 胸围B ","Price":"500一次 900两次 ","FuWu":"无套口 制服诱惑 丝袜美腿 任意姿势啪啪","Address":" 丈八北路地铁站(西安市雁塔区) 陕西省西安市雁塔区科技路82号","City":"西安","Remark":"2020-04-14 20:32","Status":null,"UserId":1001,"CreateTime":"\/Date(1586867521697)\/","CreateTimeStr":"2020-04-14 20:32","Money":5,"InfoType":null,"ClickTime":188,"GoodTime":1,"BadTime":0,"ErrorTime":0,"QueryTags":null,"IsDelete":null,"CommentCount":0,"UserName":"王者风范","UserMoney":null,"HeadImg":"/Attach/userHead/6a6b4d0e-08ce-4271-805a-41105cecc727.jpg","LastCommentTime":null,"Pic1":"http://loufeng321.cn:83\\20200414203244.jpg","Pic2":"http://loufeng321.cn:83\\20200414203258.jpg"},{"Id":39592,"Name":"西安 碑林区城南草场坡 妍妍","QQ":null,"Weixin":"ssaishanshan","Phone":"没留","JianJie":"24岁  身高164cm  体重46kg  胸围36C  ","Price":"500一次 700两次  1500包夜","FuWu":"无套口 制服诱惑 丝袜美腿 69 任意姿势啪啪","Address":"翡翠明珠(碑林区城南草场坡甲字50号) 陕西省西安市碑林区草场坡","City":"西安","Remark":"2020-04-14 20:16","Status":null,"UserId":1001,"CreateTime":"\/Date(1586866618287)\/","CreateTimeStr":"2020-04-14 20:16","Money":5,"InfoType":null,"ClickTime":116,"GoodTime":0,"BadTime":0,"ErrorTime":0,"QueryTags":null,"IsDelete":null,"CommentCount":0,"UserName":"王者风范","UserMoney":null,"HeadImg":"/Attach/userHead/6a6b4d0e-08ce-4271-805a-41105cecc727.jpg","LastCommentTime":null,"Pic1":"http://loufeng321.cn:83\\20200414201719.jpg","Pic2":"http://loufeng321.cn:83\\20200414201727.jpg"},{"Id":39423,"Name":"西安 未央区 萧家巷 茹茹","QQ":null,"Weixin":"LiuLan0314G","Phone":"18380864764","JianJie":"24岁  身高50kg  体重164cm  胸围36c","Price":"单5/双9/页20 (必须带)","FuWu":"鸳鸯浴 无套吹箫 深喉 调情风骚 波推 六九式吹箫  性爱十八式爱爱","Address":" 范唐社区食堂 陕西省西安市未央区萧家巷名京九合院锦福苑13号楼四方街1层","City":"西安","Remark":"2020-04-08 17:07","Status":null,"UserId":1001,"CreateTime":"\/Date(1586336851240)\/","CreateTimeStr":"2020-04-08 17:07","Money":5,"InfoType":null,"ClickTime":139,"GoodTime":0,"BadTime":0,"ErrorTime":0,"QueryTags":null,"IsDelete":null,"CommentCount":0,"UserName":"王者风范","UserMoney":null,"HeadImg":"/Attach/userHead/6a6b4d0e-08ce-4271-805a-41105cecc727.jpg","LastCommentTime":null,"Pic1":"http://loufeng321.cn:83\\20200408170804.jpg","Pic2":"http://loufeng321.cn:83\\20200408170810.jpg"},{"Id":39354,"Name":"西安 大明宫西 万人迷","QQ":null,"Weixin":"A13572252015","Phone":"15289383448","JianJie":"27岁左右  身高162  胸C 体重48kg   身材苗条 ","Price":"一3米，二5米。夜12米。十点到十点","FuWu":"陪洗，颜射，深猴，KB， 推，臀推，毒龙，69.aiai","Address":" 名京九合院锦福苑-西门 陕西省西安市未央区萧家巷","City":"西安","Remark":"2020-04-05 19:12","Status":null,"UserId":1001,"CreateTime":"\/Date(1586085145357)\/","CreateTimeStr":"2020-04-05 19:12","Money":5,"InfoType":null,"ClickTime":209,"GoodTime":1,"BadTime":0,"ErrorTime":0,"QueryTags":null,"IsDelete":null,"CommentCount":0,"UserName":"王者风范","UserMoney":null,"HeadImg":"/Attach/userHead/6a6b4d0e-08ce-4271-805a-41105cecc727.jpg","LastCommentTime":null,"Pic1":"http://loufeng321.cn:83\\20200405191537.jpg","Pic2":"http://loufeng321.cn:83\\20200405191543.jpg"},{"Id":39353,"Name":"西安 雁塔区 丈八北路 语焉","QQ":null,"Weixin":"huangxiaoben520","Phone":"没留","JianJie":"年龄25 身高1 60体重115胸围36D","Price":"5米一次50分钟   9米 两次70分钟","FuWu":"舔蛋蛋波推吹箫鸳鸯浴花式调 情制服诱惑各种姿势配合","Address":"丈八北路地铁站(西安市雁塔区) 陕西省西安市雁塔区科技路82号","City":"西安","Remark":"2020-04-05 18:57","Status":null,"UserId":1001,"CreateTime":"\/Date(1586084225230)\/","CreateTimeStr":"2020-04-05 18:57","Money":5,"InfoType":null,"ClickTime":243,"GoodTime":1,"BadTime":0,"ErrorTime":0,"QueryTags":null,"IsDelete":null,"CommentCount":0,"UserName":"王者风范","UserMoney":null,"HeadImg":"/Attach/userHead/6a6b4d0e-08ce-4271-805a-41105cecc727.jpg","LastCommentTime":null,"Pic1":"http://loufeng321.cn:83\\20200405185742.jpg","Pic2":"http://loufeng321.cn:83\\20200405185749.jpg"},{"Id":39352,"Name":"西安 南稍门 舒心","QQ":null,"Weixin":"xilaideng0000","Phone":"没留","JianJie":"南方妹妹 163高 体重110斤  胸围36C","Price":"单5米  双9米(限时单50双70)","FuWu":"胸推漫游(无套吹)激情啪啪(必 须带帽)制服高跟十分配合单","Address":"肉魁屋烧肉酒场(南稍门店) 陕西省西安市碑林区永宁路58号大话南门5幢一层商铺","City":"西安","Remark":"2020-04-05 18:52","Status":null,"UserId":1001,"CreateTime":"\/Date(1586083936857)\/","CreateTimeStr":"2020-04-05 18:52","Money":5,"InfoType":null,"ClickTime":97,"GoodTime":1,"BadTime":0,"ErrorTime":0,"QueryTags":null,"IsDelete":null,"CommentCount":0,"UserName":"王者风范","UserMoney":null,"HeadImg":"/Attach/userHead/6a6b4d0e-08ce-4271-805a-41105cecc727.jpg","LastCommentTime":null,"Pic1":"http://loufeng321.cn:83\\20200405185236.jpg","Pic2":"http://loufeng321.cn:83\\20200405185243.jpg"},{"Id":37200,"Name":"西安 碑林区草场坡 西西","QQ":null,"Weixin":"XC15981656359","Phone":"没留","JianJie":"24岁 身高165cm  体重95斤  胸围C  肤白貌美 身材苗条","Price":"一节5 两节7 ","FuWu":"口合作姿势配合陪洗","Address":"长安大街3号C座 陕西省西安市碑林区草场坡南口","City":"西安","Remark":"2020-03-29 16:12","Status":null,"UserId":1001,"CreateTime":"\/Date(1585469534707)\/","CreateTimeStr":"2020-03-29 16:12","Money":5,"InfoType":null,"ClickTime":180,"GoodTime":0,"BadTime":0,"ErrorTime":0,"QueryTags":null,"IsDelete":null,"CommentCount":0,"UserName":"王者风范","UserMoney":null,"HeadImg":"/Attach/userHead/6a6b4d0e-08ce-4271-805a-41105cecc727.jpg","LastCommentTime":null,"Pic1":"http://loufeng321.cn:83\\20200329161259.jpg","Pic2":null},{"Id":37199,"Name":"西安 碑林区草场坡 秋子","QQ":null,"Weixin":"AA1582404","Phone":"没留","JianJie":"26岁 身高165  体重98  胸围36D  ","Price":"500一次 700两次   包夜1300","FuWu":"洗吹做 一般的都有","Address":"长安大街3号C座 陕西省西安市碑林区草场坡南口","City":"西安","Remark":"2020-03-29 16:06","Status":null,"UserId":1001,"CreateTime":"\/Date(1585469195213)\/","CreateTimeStr":"2020-03-29 16:06","Money":5,"InfoType":null,"ClickTime":137,"GoodTime":0,"BadTime":0,"ErrorTime":0,"QueryTags":null,"IsDelete":null,"CommentCount":0,"UserName":"王者风范","UserMoney":null,"HeadImg":"/Attach/userHead/6a6b4d0e-08ce-4271-805a-41105cecc727.jpg","LastCommentTime":null,"Pic1":"http://loufeng321.cn:83\\20200329160707.jpg","Pic2":"http://loufeng321.cn:83\\20200329160714.jpg"},{"Id":37197,"Name":"西安 莲湖区 二环路 琳达","QQ":null,"Weixin":"LinChu7890","Phone":"没留","JianJie":"19岁 身高170 体重102  胸围38C","Price":"500一次 800两次 1000两小时不限次","FuWu":"无套口 制服诱惑 丝袜美腿 接吻 69 任意姿势啪啪","Address":"嘉天smart 陕西省西安市莲湖区二环路沿线商业经济带新桃园","City":"西安","Remark":"2020-03-29 15:49","Status":null,"UserId":1001,"CreateTime":"\/Date(1585468154957)\/","CreateTimeStr":"2020-03-29 15:49","Money":5,"InfoType":null,"ClickTime":277,"GoodTime":2,"BadTime":0,"ErrorTime":0,"QueryTags":null,"IsDelete":null,"CommentCount":1,"UserName":"王者风范","UserMoney":null,"HeadImg":"/Attach/userHead/6a6b4d0e-08ce-4271-805a-41105cecc727.jpg","LastCommentTime":"\/Date(1588404005023)\/","Pic1":"http://loufeng321.cn:83\\20200329154940.jpg","Pic2":"http://loufeng321.cn:83\\20200329154945.jpg"},{"Id":37196,"Name":"西安 未央区 北二环 小漫","QQ":null,"Weixin":"lin52088k","Phone":"没留","JianJie":"23岁 身高164  体重92斤  胸围36B","Price":"单次6米  双次11米","FuWu":"无套口 制服诱惑 丝袜美腿 任意姿势啪啪","Address":" 名京九合院充电站 陕西省西安市未央区北二环名京九合院萧家北巷11号楼北","City":"西安","Remark":"2020-03-29 15:43","Status":null,"UserId":1001,"CreateTime":"\/Date(1585467830370)\/","CreateTimeStr":"2020-03-29 15:43","Money":5,"InfoType":null,"ClickTime":167,"GoodTime":1,"BadTime":0,"ErrorTime":0,"QueryTags":null,"IsDelete":null,"CommentCount":0,"UserName":"王者风范","UserMoney":null,"HeadImg":"/Attach/userHead/6a6b4d0e-08ce-4271-805a-41105cecc727.jpg","LastCommentTime":null,"Pic1":"http://loufeng321.cn:83\\20200329154450.jpg","Pic2":"http://loufeng321.cn:83\\20200329154457.jpg"},{"Id":37102,"Name":"西安 未央区 百家乐购物广场  小艾","QQ":null,"Weixin":"xd789122","Phone":"没留","JianJie":"24岁 身高163  体重96斤  胸围36","Price":"500一次 900两次  2000包夜","FuWu":"无套口 制服诱惑 丝袜美腿 任意姿势啪啪","Address":"百家乐购物广场 陕西省西安市未央区萧家村名京九合院","City":"西安","Remark":"2020-03-23 18:37","Status":null,"UserId":1001,"CreateTime":"\/Date(1584959866197)\/","CreateTimeStr":"2020-03-23 18:37","Money":5,"InfoType":null,"ClickTime":99,"GoodTime":0,"BadTime":0,"ErrorTime":0,"QueryTags":null,"IsDelete":null,"CommentCount":0,"UserName":"王者风范","UserMoney":null,"HeadImg":"/Attach/userHead/6a6b4d0e-08ce-4271-805a-41105cecc727.jpg","LastCommentTime":null,"Pic1":"http://loufeng321.cn:83\\20200323183803.jpg","Pic2":"http://loufeng321.cn:83\\20200323183808.jpg"},{"Id":36978,"Name":"西安 碑林区 草场坡南 冰冰","QQ":null,"Weixin":"ok258012341","Phone":"没留","JianJie":"24岁 身高166cm  体重98斤  胸围36C  ","Price":"单节5 两节7 夜1200","FuWu":"口合作姿势配合陪洗丝袜高跟调情诱惑亲吻69 推","Address":"长安大街3号B座 陕西省西安市碑林区草场坡南口","City":"西安","Remark":"2020-03-17 16:20","Status":null,"UserId":1001,"CreateTime":"\/Date(1584433222857)\/","CreateTimeStr":"2020-03-17 16:20","Money":5,"InfoType":null,"ClickTime":192,"GoodTime":1,"BadTime":0,"ErrorTime":0,"QueryTags":null,"IsDelete":null,"CommentCount":0,"UserName":"王者风范","UserMoney":null,"HeadImg":"/Attach/userHead/6a6b4d0e-08ce-4271-805a-41105cecc727.jpg","LastCommentTime":null,"Pic1":"http://loufeng321.cn:83\\20200317162154.jpg","Pic2":null},{"Id":36859,"Name":"西安 碑林区 骄阳贝儿第三幼稚园 乐乐","QQ":null,"Weixin":"15134398786","Phone":"15134398786","JianJie":"26岁  身高165  体重96  胸围C  漂亮 气质好","Price":"400一次 700两次","FuWu":"鸳鸯浴 无套吹箫 深喉 调情风骚 波推 六九式吹箫  性爱十八式爱爱","Address":"骄阳贝儿第三幼稚园 陕西省西安市碑林区五道十字南街与北郭门交叉口东南50米","City":"西安","Remark":"2020-03-12 18:45","Status":null,"UserId":1001,"CreateTime":"\/Date(1584009945747)\/","CreateTimeStr":"2020-03-12 18:45","Money":5,"InfoType":null,"ClickTime":142,"GoodTime":0,"BadTime":0,"ErrorTime":0,"QueryTags":null,"IsDelete":null,"CommentCount":0,"UserName":"王者风范","UserMoney":null,"HeadImg":"/Attach/userHead/6a6b4d0e-08ce-4271-805a-41105cecc727.jpg","LastCommentTime":null,"Pic1":"http://loufeng321.cn:83\\20200312184625.jpg","Pic2":"http://loufeng321.cn:83\\20200312184630.jpg"},{"Id":36691,"Name":"西安 未央区 万象城 娜娜","QQ":null,"Weixin":"lpzd2011528；TL2011528","Phone":"没留","JianJie":"31岁  身高1.68米  体重98斤  胸围36D","Price":"单4双7，包夜十一点后1300","FuWu":"可陪洗制服丝袜69 kb深喉性格风骚妩媚配合各种姿势","Address":"万象城B座 陕西省西安市未央区三桥新街1076号","City":"西安","Remark":"2020-03-02 11:11","Status":null,"UserId":1001,"CreateTime":"\/Date(1583118709757)\/","CreateTimeStr":"2020-03-02 11:11","Money":5,"InfoType":null,"ClickTime":264,"GoodTime":0,"BadTime":0,"ErrorTime":0,"QueryTags":null,"IsDelete":null,"CommentCount":0,"UserName":"王者风范","UserMoney":null,"HeadImg":"/Attach/userHead/6a6b4d0e-08ce-4271-805a-41105cecc727.jpg","LastCommentTime":null,"Pic1":"http://loufeng321.cn:83\\20200302111444.jpg","Pic2":"http://loufeng321.cn:83\\20200302111453.jpg"},{"Id":36545,"Name":"西安 碑林区 草场坡 味道","QQ":null,"Weixin":"zls323424","Phone":"没留","JianJie":"25岁 身高165  体重115斤 胸围36D 皮肤白皙 活好水多 ","Price":"500一次 700两次   包夜1500","FuWu":"鸳鸯浴 无套吹箫 深喉 调情风骚 波推 六九式吹箫  性爱十八式爱爱","Address":"翡翠明珠(碑林区城南草场坡甲字50号) 陕西省西安市碑林区草场坡","City":"西安","Remark":"2020-02-22 20:17","Status":null,"UserId":1001,"CreateTime":"\/Date(1582373832700)\/","CreateTimeStr":"2020-02-22 20:17","Money":5,"InfoType":null,"ClickTime":234,"GoodTime":0,"BadTime":0,"ErrorTime":0,"QueryTags":null,"IsDelete":null,"CommentCount":0,"UserName":"王者风范","UserMoney":null,"HeadImg":"/Attach/userHead/6a6b4d0e-08ce-4271-805a-41105cecc727.jpg","LastCommentTime":null,"Pic1":"http://loufeng321.cn:83\\20200222201756.jpg","Pic2":"http://loufeng321.cn:83\\20200222201802.jpg"},{"Id":34400,"Name":"西安 未央区 未央路方新村 蔓蔓","QQ":null,"Weixin":"beijiaomeimei","Phone":"没留","JianJie":"24岁 身高164cm  体重92斤  胸围36B  肤白貌美","Price":"600一次  1100两次 ","FuWu":"鸳鸯浴 无套吹箫 深喉 调情风骚 波推 六九式吹箫  性爱十八式爱爱","Address":"海友酒店(龙首商业街店) 陕西省西安市未央区未央路方新村65号","City":"西安","Remark":"2020-02-05 18:37","Status":null,"UserId":1001,"CreateTime":"\/Date(1580899028623)\/","CreateTimeStr":"2020-02-05 18:37","Money":5,"InfoType":null,"ClickTime":380,"GoodTime":0,"BadTime":0,"ErrorTime":0,"QueryTags":null,"IsDelete":null,"CommentCount":1,"UserName":"王者风范","UserMoney":null,"HeadImg":"/Attach/userHead/6a6b4d0e-08ce-4271-805a-41105cecc727.jpg","LastCommentTime":"\/Date(1582900170757)\/","Pic1":"http://loufeng321.cn:83\\20200203183742.jpg","Pic2":"http://loufeng321.cn:83\\20200203183827.jpg"},{"Id":34375,"Name":"西安 未央区 未央路方新村 蔓蔓","QQ":null,"Weixin":"beijiaomeimei","Phone":"没留","JianJie":"24岁 身高164cm  体重92斤  胸围36B  肤白貌美","Price":"600一次  1100两次 ","FuWu":"鸳鸯浴 无套吹箫 深喉 调情风骚 波推 六九式吹箫  性爱十八式爱爱","Address":"海友酒店(龙首商业街店) 陕西省西安市未央区未央路方新村65号","City":"西安","Remark":"2020-02-03 18:37","Status":null,"UserId":1001,"CreateTime":"\/Date(1580726228623)\/","CreateTimeStr":"2020-02-03 18:37","Money":5,"InfoType":null,"ClickTime":476,"GoodTime":0,"BadTime":0,"ErrorTime":0,"QueryTags":null,"IsDelete":null,"CommentCount":3,"UserName":"王者风范","UserMoney":null,"HeadImg":"/Attach/userHead/6a6b4d0e-08ce-4271-805a-41105cecc727.jpg","LastCommentTime":"\/Date(1595743682700)\/","Pic1":"http://loufeng321.cn:83\\20200203183742.jpg","Pic2":"http://loufeng321.cn:83\\20200203183827.jpg"},{"Id":34295,"Name":"西安 未央区 萧家巷 小S","QQ":null,"Weixin":"king-Mr-liu1314","Phone":"16573971098  支付宝账号","JianJie":"24岁 身高168  体重96  胸围C  皮肤白皙  身材火辣 淑女范  活泼开朗  清纯甜美","Price":"500一次 900两次  2000包夜","FuWu":"无套口 制服诱惑 丝袜美腿 KB  69 DL 任意姿势啪啪","Address":"范唐life社区食堂 陕西省西安市未央区萧家巷名京九合院锦福苑13号楼四方街1层","City":"西安","Remark":"2020-01-29 16:50","Status":null,"UserId":1001,"CreateTime":"\/Date(1580287806493)\/","CreateTimeStr":"2020-01-29 16:50","Money":5,"InfoType":null,"ClickTime":144,"GoodTime":0,"BadTime":0,"ErrorTime":0,"QueryTags":null,"IsDelete":null,"CommentCount":0,"UserName":"王者风范","UserMoney":null,"HeadImg":"/Attach/userHead/6a6b4d0e-08ce-4271-805a-41105cecc727.jpg","LastCommentTime":null,"Pic1":"http://loufeng321.cn:83\\20200129165053.jpg","Pic2":"http://loufeng321.cn:83\\20200129165100.jpg"},{"Id":34261,"Name":"西安 碑林区 长安北路 闹闹","QQ":null,"Weixin":"huaduo121","Phone":"没留","JianJie":"26岁  身高165  体重95  胸围34B   ","Price":"500一次 700两次   包夜1200","FuWu":"无套口 制服诱惑 丝袜美腿 任意姿势啪啪","Address":"翡翠明珠(碑林区城南草场坡甲字50号) 陕西省西安市碑林区长安北路33号","City":"西安","Remark":"2020-01-25 17:21","Status":null,"UserId":1001,"CreateTime":"\/Date(1579944088173)\/","CreateTimeStr":"2020-01-25 17:21","Money":5,"InfoType":null,"ClickTime":425,"GoodTime":1,"BadTime":0,"ErrorTime":0,"QueryTags":null,"IsDelete":null,"CommentCount":1,"UserName":"王者风范","UserMoney":null,"HeadImg":"/Attach/userHead/6a6b4d0e-08ce-4271-805a-41105cecc727.jpg","LastCommentTime":"\/Date(1580699671640)\/","Pic1":"http://loufeng321.cn:83\\20200123172155.jpg","Pic2":"http://loufeng321.cn:83\\20200123172201.jpg"},{"Id":34213,"Name":"西安 碑林区 长安北路 闹闹","QQ":null,"Weixin":"huaduo121","Phone":"没留","JianJie":"26岁  身高165  体重95  胸围34B   ","Price":"500一次 700两次   包夜1200","FuWu":"无套口 制服诱惑 丝袜美腿 任意姿势啪啪","Address":"翡翠明珠(碑林区城南草场坡甲字50号) 陕西省西安市碑林区长安北路33号","City":"西安","Remark":"2020-01-23 17:21","Status":null,"UserId":1001,"CreateTime":"\/Date(1579771288173)\/","CreateTimeStr":"2020-01-23 17:21","Money":5,"InfoType":null,"ClickTime":141,"GoodTime":1,"BadTime":0,"ErrorTime":0,"QueryTags":null,"IsDelete":null,"CommentCount":0,"UserName":"王者风范","UserMoney":null,"HeadImg":"/Attach/userHead/6a6b4d0e-08ce-4271-805a-41105cecc727.jpg","LastCommentTime":null,"Pic1":"http://loufeng321.cn:83\\20200123172155.jpg","Pic2":"http://loufeng321.cn:83\\20200123172201.jpg"},{"Id":34129,"Name":"西安 未央区 萧家巷 辣妹子","QQ":null,"Weixin":"yangchuxin9","Phone":"没留","JianJie":"25岁 身高166  体重50kg  胸围D  活泼可爱  性格开朗 清纯甜美 调情高手","Price":"500一次 900两次  2000包夜","FuWu":"鸳鸯浴 无套吹箫 深喉 调情风骚 波推 六九式吹箫  性爱十八式爱爱","Address":" 范唐life社区食堂 陕西省西安市未央区萧家巷名京九合院锦福苑13号楼四方街1层","City":"西安","Remark":"2020-01-18 19:14","Status":null,"UserId":1001,"CreateTime":"\/Date(1579346041960)\/","CreateTimeStr":"2020-01-18 19:14","Money":5,"InfoType":null,"ClickTime":320,"GoodTime":1,"BadTime":0,"ErrorTime":0,"QueryTags":null,"IsDelete":null,"CommentCount":1,"UserName":"王者风范","UserMoney":null,"HeadImg":"/Attach/userHead/6a6b4d0e-08ce-4271-805a-41105cecc727.jpg","LastCommentTime":"\/Date(1584519260597)\/","Pic1":"http://loufeng321.cn:83\\20200118191426.jpg","Pic2":"http://loufeng321.cn:83\\20200118191434.jpg"},{"Id":33996,"Name":"西安 未央区荣民路 妃儿","QQ":null,"Weixin":"aifeier-777","Phone":"没留","JianJie":"25岁 身高162  体重100斤 胸围36C ","Price":"单次500  双次900  包夜20","FuWu":"鸳鸯浴 无套吹箫  调情风骚 波推 六九式吹箫  性爱十八式爱爱","Address":"洋洋烤肉 陕西省西安市未央区荣民路凤城南路19号","City":"西安","Remark":"2020-01-11 11:43","Status":null,"UserId":1001,"CreateTime":"\/Date(1578714205107)\/","CreateTimeStr":"2020-01-11 11:43","Money":5,"InfoType":null,"ClickTime":214,"GoodTime":0,"BadTime":0,"ErrorTime":0,"QueryTags":null,"IsDelete":null,"CommentCount":0,"UserName":"王者风范","UserMoney":null,"HeadImg":"/Attach/userHead/6a6b4d0e-08ce-4271-805a-41105cecc727.jpg","LastCommentTime":null,"Pic1":"http://loufeng321.cn:83\\20200111114343.jpg","Pic2":"http://loufeng321.cn:83\\20200111114348.jpg"},{"Id":33995,"Name":"西安 碑林区 城南草场坡 百合","QQ":null,"Weixin":"aghu56789","Phone":"没留","JianJie":"23岁 身高164  体重48kg  胸围C ","Price":"500一杯","FuWu":"鸳鸯浴 无套吹箫 深喉 调情风骚 波推 六九式吹箫  性爱十八式爱爱","Address":" 翡翠明珠 陕西省西安市碑林区城南草场坡甲字50号","City":"西安","Remark":"2020-01-11 11:34","Status":null,"UserId":1001,"CreateTime":"\/Date(1578713669410)\/","CreateTimeStr":"2020-01-11 11:34","Money":5,"InfoType":null,"ClickTime":162,"GoodTime":1,"BadTime":0,"ErrorTime":0,"QueryTags":null,"IsDelete":null,"CommentCount":0,"UserName":"王者风范","UserMoney":null,"HeadImg":"/Attach/userHead/6a6b4d0e-08ce-4271-805a-41105cecc727.jpg","LastCommentTime":null,"Pic1":"http://loufeng321.cn:83\\20200111113445.jpg","Pic2":"http://loufeng321.cn:83\\20200111113450.jpg"},{"Id":33901,"Name":"西安 雁塔区 兰岛广场 缅甸混血妹儿","QQ":null,"Weixin":"kjl0505","Phone":"没留","JianJie":"25岁 身高166cm 体重54kg  胸围36D 皮肤白皙 性格开朗 温柔体贴","Price":"500一次 900两次  2000包夜","FuWu":"鸳鸯浴 无套吹箫 深喉 调情风骚 波推 六九式吹箫  性爱十八式爱爱","Address":"兰岛广场 陕西省西安市雁塔区科技六路4号","City":"西安","Remark":"2020-01-05 16:20","Status":null,"UserId":1001,"CreateTime":"\/Date(1578212419780)\/","CreateTimeStr":"2020-01-05 16:20","Money":5,"InfoType":null,"ClickTime":152,"GoodTime":0,"BadTime":0,"ErrorTime":0,"QueryTags":null,"IsDelete":null,"CommentCount":0,"UserName":"王者风范","UserMoney":null,"HeadImg":"/Attach/userHead/6a6b4d0e-08ce-4271-805a-41105cecc727.jpg","LastCommentTime":null,"Pic1":"http://loufeng321.cn:83\\20200105162047.jpg","Pic2":"http://loufeng321.cn:83\\20200105162053.jpg"},{"Id":33898,"Name":"西安 碑林区永宁路 七月","QQ":"1032743333","Weixin":"liyisheng27","Phone":"没留","JianJie":"24岁 身高165cm  体重95斤  胸围C  肤白貌美","Price":"500一次","FuWu":"无套口 制服诱惑 丝袜美腿 任意姿势啪啪","Address":"长安壹栋 陕西省西安市碑林区永宁路10号西南方向50米","City":"西安","Remark":"2020-01-05 15:44","Status":null,"UserId":1001,"CreateTime":"\/Date(1578210244537)\/","CreateTimeStr":"2020-01-05 15:44","Money":5,"InfoType":null,"ClickTime":191,"GoodTime":0,"BadTime":0,"ErrorTime":0,"QueryTags":null,"IsDelete":null,"CommentCount":0,"UserName":"王者风范","UserMoney":null,"HeadImg":"/Attach/userHead/6a6b4d0e-08ce-4271-805a-41105cecc727.jpg","LastCommentTime":null,"Pic1":"http://loufeng321.cn:83\\20200105154441.jpg","Pic2":"http://loufeng321.cn:83\\20200105154525.jpg"},{"Id":33761,"Name":"西安 碑林区城南草场坡 姗姗","QQ":null,"Weixin":"aiaiaijiaobaba","Phone":"没留","JianJie":"25岁  身高163  体重46kg  胸围34C  肤白貌美 身材苗条性感","Price":"500一次 700两次","FuWu":"鸳鸯浴  波推 臀推 漫游 69  口活 丝袜制服诱惑 ML","Address":"翡翠明珠 陕西省西安市碑林区城南草场坡甲字50号","City":"西安","Remark":"2019-12-28 13:57","Status":null,"UserId":1001,"CreateTime":"\/Date(1577512625207)\/","CreateTimeStr":"2019-12-28 13:57","Money":5,"InfoType":null,"ClickTime":153,"GoodTime":0,"BadTime":0,"ErrorTime":0,"QueryTags":null,"IsDelete":null,"CommentCount":0,"UserName":"王者风范","UserMoney":null,"HeadImg":"/Attach/userHead/6a6b4d0e-08ce-4271-805a-41105cecc727.jpg","LastCommentTime":null,"Pic1":"http://loufeng321.cn:83\\20191228135731.jpg","Pic2":"http://loufeng321.cn:83\\20191228135737.jpg"},{"Id":33752,"Name":"西安 未央区西咸新区 婷婷","QQ":null,"Weixin":"zmh13233071801","Phone":"没留","JianJie":"28岁  1.60米  胸围36C 体重96斤  ","Price":"400一次 700两次 1200包夜","FuWu":"陪浴 口活 深喉  漫游 69  观音坐莲 丝袜高跟制服诱惑  戴套做  ","Address":"小韩烤肉(三桥店) 陕西省西安市未央区西咸新区沣东新城安置新村5排1栋1号","City":"西安","Remark":"2019-12-28 11:11","Status":null,"UserId":1001,"CreateTime":"\/Date(1577502704147)\/","CreateTimeStr":"2019-12-28 11:11","Money":10,"InfoType":null,"ClickTime":100,"GoodTime":3,"BadTime":0,"ErrorTime":0,"QueryTags":null,"IsDelete":null,"CommentCount":0,"UserName":"王者风范","UserMoney":null,"HeadImg":"/Attach/userHead/6a6b4d0e-08ce-4271-805a-41105cecc727.jpg","LastCommentTime":null,"Pic1":"http://loufeng321.cn:83\\20191228111216.jpg","Pic2":"http://loufeng321.cn:83\\20191228111224.jpg"},{"Id":33004,"Name":"西安 未央区 萧家北巷 莹莹","QQ":"3359452127","Weixin":"kkmm17726 ","Phone":"没留","JianJie":"23岁 身高165cm  体重45kg  胸围36C 活泼可爱 性格开朗 清纯甜美","Price":"500一次  900两次  2000by","FuWu":"鸳鸯浴  波推 臀推 漫游 69  口活 丝袜制服诱惑 ML","Address":"名京九合院锦绣苑7号楼 陕西省西安市未央区萧家北巷","City":"西安","Remark":"2019-11-02 20:34","Status":null,"UserId":1001,"CreateTime":"\/Date(1572698090013)\/","CreateTimeStr":"2019-11-02 20:34","Money":10,"InfoType":null,"ClickTime":206,"GoodTime":1,"BadTime":0,"ErrorTime":0,"QueryTags":null,"IsDelete":null,"CommentCount":0,"UserName":"王者风范","UserMoney":null,"HeadImg":"/Attach/userHead/6a6b4d0e-08ce-4271-805a-41105cecc727.jpg","LastCommentTime":null,"Pic1":"http://loufeng321.cn:83\\20191102203517.jpg","Pic2":"http://loufeng321.cn:83\\20191102203525.jpg"},{"Id":31572,"Name":"未央区未央路 逸儿","QQ":"928543203","Weixin":null,"Phone":"没留","JianJie":"25岁 158cm  体重100斤  胸围36D  服务热情周到  态度好","Price":"500一次  900两次  2000by","FuWu":"陪浴 口活 深喉  漫游 69  观音坐莲 丝袜高跟制服诱惑  戴套做  ","Address":"陕西省西安市未央区未央路164号","City":"西安","Remark":"2019-10-15 22:13","Status":null,"UserId":1001,"CreateTime":"\/Date(1571148838830)\/","CreateTimeStr":"2019-10-15 22:13","Money":10,"InfoType":null,"ClickTime":169,"GoodTime":9,"BadTime":0,"ErrorTime":0,"QueryTags":null,"IsDelete":null,"CommentCount":0,"UserName":"王者风范","UserMoney":null,"HeadImg":"/Attach/userHead/6a6b4d0e-08ce-4271-805a-41105cecc727.jpg","LastCommentTime":null,"Pic1":"http://loufeng321.cn:83\\20190831214751.jpg","Pic2":"http://loufeng321.cn:83\\20190831214835.jpg"},{"Id":31032,"Name":"雁塔 兰岛广场 小晴晴","QQ":"463220048","Weixin":"ye-er2000","Phone":"没留","JianJie":"年龄20 身高162 胸围34b 皮肤白嫩  性格温柔","Price":"5张一次 （50分钟）8张两次（70分钟）夜20张（11/8） ","FuWu":" 洗澡 无套口波推 丝*制服 过水  （出*算一次）调情爱爱  姿势任意 态度好 各种配合","Address":"西安兰岛广场 陕西省西安市雁塔区科技六路26西南方向69米","City":"西安","Remark":"2019-10-15 22:13","Status":null,"UserId":1001,"CreateTime":"\/Date(1571148838830)\/","CreateTimeStr":"2019-10-15 22:13","Money":10,"InfoType":null,"ClickTime":121,"GoodTime":9,"BadTime":0,"ErrorTime":0,"QueryTags":null,"IsDelete":null,"CommentCount":0,"UserName":"王者风范","UserMoney":null,"HeadImg":"/Attach/userHead/6a6b4d0e-08ce-4271-805a-41105cecc727.jpg","LastCommentTime":null,"Pic1":"http://loufeng321.cn:83\\20190810203422.jpg","Pic2":"http://loufeng321.cn:83\\20190810203505.jpg"},{"Id":1029,"Name":"安康三星宾馆dp爽","QQ":null,"Weixin":null,"Phone":"没留","JianJie":"19-25  妹子资源多","Price":"全套300，快餐200.包夜500","FuWu":"全套，快餐.kj，DP.RJ.SWQS","Address":" 陕西省安康市汉滨区巴山中路78号   ","City":"安康","Remark":"2019-10-15 22:13","Status":null,"UserId":1001,"CreateTime":"\/Date(1571148838830)\/","CreateTimeStr":"2019-10-15 22:13","Money":20,"InfoType":null,"ClickTime":215,"GoodTime":9,"BadTime":0,"ErrorTime":0,"QueryTags":null,"IsDelete":null,"CommentCount":0,"UserName":"王者风范","UserMoney":null,"HeadImg":"/Attach/userHead/6a6b4d0e-08ce-4271-805a-41105cecc727.jpg","LastCommentTime":null,"Pic1":null,"Pic2":null},{"Id":615,"Name":"延安市场沟红日足浴东北妞爽记 ","QQ":"直接去","Weixin":null,"Phone":"人家不给，没办法","JianJie":"25-35  技术非常棒","Price":"DP/150包夜/400","FuWu":"DPKJ足浴","Address":"陕西省延安市宝塔区市场沟红日足浴     ","City":"延安","Remark":"2019-10-15 22:13","Status":null,"UserId":1001,"CreateTime":"\/Date(1571148838830)\/","CreateTimeStr":"2019-10-15 22:13","Money":10,"InfoType":null,"ClickTime":177,"GoodTime":9,"BadTime":0,"ErrorTime":0,"QueryTags":null,"IsDelete":null,"CommentCount":0,"UserName":"王者风范","UserMoney":null,"HeadImg":"/Attach/userHead/6a6b4d0e-08ce-4271-805a-41105cecc727.jpg","LastCommentTime":null,"Pic1":null,"Pic2":null}]}