{"count":0,"code":0,"msg":null,"data":[{"Id":40307,"Name":"双鸭山 福利熟女爽记","QQ":null,"Weixin":"18404600536","Phone":"没留","JianJie":"自己找的 刚开始没跟她明说 她直接给我打过来电话了 一看有戏 正好她在福利 直接去福利找个地方 来双鸭山也行 报销路费就可以 30多 不胖不瘦 态度挺好 加上微信直接就跟她说就行","Price":"200一次","FuWu":"洗吹做 一般的都有","Address":"双鸭山市微信联系","City":"双鸭山","Remark":"2020-05-09 13:36","Status":null,"UserId":1001,"CreateTime":"\/Date(1589002566133)\/","CreateTimeStr":"2020-05-09 13:36","Money":5,"InfoType":null,"ClickTime":134,"GoodTime":2,"BadTime":0,"ErrorTime":0,"QueryTags":null,"IsDelete":null,"CommentCount":0,"UserName":"王者风范","UserMoney":null,"HeadImg":"/Attach/userHead/6a6b4d0e-08ce-4271-805a-41105cecc727.jpg","LastCommentTime":null,"Pic1":"http://loufeng321.cn:83\\20200509133627.jpeg","Pic2":null}]}